{"t": "\u00a7 38\u2013821.01(Perm). Definitions.", "p": "/us/dc/council/code/sections/38-821.01(Perm)", "et": "section", "dj": "/us/dc/council/code/index.json", "fh": "/us/dc/council/code/sections/38-821.01(Perm)/index.html", "sc": "\u00a7 38-821.01(Perm)", "rp": "\u00a738-821.01(Perm)", "sp": "library|D.C. Code|99|38-821.01(Perm)", "c": [{"t": "(a)", "p": "/us/dc/council/code/sections/38-821.01(Perm)#", "et": "para", "sc": "\u00a7 38-821.01(Perm)", "rp": "\u00a738-821.01(Perm)", "c": [{"t": "(1)", "p": "/us/dc/council/code/sections/38-821.01(Perm)#(1)", "et": "para", "sc": "\u00a7 38-821.01(Perm)(1)", "rp": "\u00a738-821.01(Perm)|(1)", "c": [{"t": "(A)", "p": "/us/dc/council/code/sections/38-821.01(Perm)#(1)(A)", "et": "para", "sc": "\u00a7 38-821.01(Perm)(1)(A)", "rp": "\u00a738-821.01(Perm)|(1)|(A)", "c": [{"t": "(i)", "p": "/us/dc/council/code/sections/38-821.01(Perm)#(1)(A)(i)", "et": "para", "sc": "\u00a7 38-821.01(Perm)(1)(A)(i)", "rp": "\u00a738-821.01(Perm)|(1)|(A)|(i)", "x": "Offered in one or more locations with high student traffic other than the c"}, {"t": "(ii)", "p": "/us/dc/council/code/sections/38-821.01(Perm)#(1)(A)(ii)", "et": "para", "sc": "\u00a7 38-821.01(Perm)(1)(A)(ii)", "rp": "\u00a738-821.01(Perm)|(1)|(A)|(ii)", "x": "Available after the start of the school day or both before and after the st"}], "x": "Such as breakfast in the classroom or breakfast on grab-and-go carts, in wh"}, {"t": "(B)", "p": "/us/dc/council/code/sections/38-821.01(Perm)#(1)(B)", "et": "para", "sc": "\u00a7 38-821.01(Perm)(1)(B)", "rp": "\u00a738-821.01(Perm)|(1)|(B)", "x": "That has been proven to increase student participation in breakfast relativ"}], "x": "\"Alternative breakfast serving model\" means a model of serving breakfast:"}, {"t": "(1A)", "p": "/us/dc/council/code/sections/38-821.01(Perm)#(1A)", "et": "para", "sc": "\u00a7 38-821.01(Perm)(1A)", "rp": "\u00a738-821.01(Perm)|(1A)", "x": "\"Animal product\" means meat, poultry, seafood, dairy, eggs, honey, and any "}, {"t": "(1B)", "p": "/us/dc/council/code/sections/38-821.01(Perm)#(1B)", "et": "para", "sc": "\u00a7 38-821.01(Perm)(1B)", "rp": "\u00a738-821.01(Perm)|(1B)", "x": "\"Breakfast in the classroom\" means an alternative breakfast serving model w"}, {"t": "(1C)", "p": "/us/dc/council/code/sections/38-821.01(Perm)#(1C)", "et": "para", "sc": "\u00a7 38-821.01(Perm)(1C)", "rp": "\u00a738-821.01(Perm)|(1C)", "c": [{"t": "(A)", "p": "/us/dc/council/code/sections/38-821.01(Perm)#(1C)(A)", "et": "para", "sc": "\u00a7 38-821.01(Perm)(1C)(A)", "rp": "\u00a738-821.01(Perm)|(1C)|(A)", "x": "\"Drinking water source\" means a source of water from which a person can rea"}, {"t": "(B)", "p": "/us/dc/council/code/sections/38-821.01(Perm)#(1C)(B)", "et": "para", "sc": "\u00a7 38-821.01(Perm)(1C)(B)", "rp": "\u00a738-821.01(Perm)|(1C)|(B)", "x": "\"Drinking water source\" shall not include a source of water for which a pub"}]}, {"t": "(1D)", "p": "/us/dc/council/code/sections/38-821.01(Perm)#(1D)", "et": "para", "sc": "\u00a7 38-821.01(Perm)(1D)", "rp": "\u00a738-821.01(Perm)|(1D)", "x": "\"Formula grants process\" means a process developed by OSSE to distribute gr"}, {"t": "(1E)", "p": "/us/dc/council/code/sections/38-821.01(Perm)#(1E)", "et": "para", "sc": "\u00a7 38-821.01(Perm)(1E)", "rp": "\u00a738-821.01(Perm)|(1E)", "c": [{"t": "(A)", "p": "/us/dc/council/code/sections/38-821.01(Perm)#(1E)(A)", "et": "para", "sc": "\u00a7 38-821.01(Perm)(1E)(A)", "rp": "\u00a738-821.01(Perm)|(1E)|(A)", "x": "Local economics;"}, {"t": "(B)", "p": "/us/dc/council/code/sections/38-821.01(Perm)#(1E)(B)", "et": "para", "sc": "\u00a7 38-821.01(Perm)(1E)(B)", "rp": "\u00a738-821.01(Perm)|(1E)|(B)", "x": "Nutrition;"}, {"t": "(C)", "p": "/us/dc/council/code/sections/38-821.01(Perm)#(1E)(C)", "et": "para", "sc": "\u00a7 38-821.01(Perm)(1E)(C)", "rp": "\u00a738-821.01(Perm)|(1E)|(C)", "x": "Valued workforce;"}, {"t": "(D)", "p": "/us/dc/council/code/sections/38-821.01(Perm)#(1E)(D)", "et": "para", "sc": "\u00a7 38-821.01(Perm)(1E)(D)", "rp": "\u00a738-821.01(Perm)|(1E)|(D)", "x": "Environmental sustainability; and"}, {"t": "(E)", "p": "/us/dc/council/code/sections/38-821.01(Perm)#(1E)(E)", "et": "para", "sc": "\u00a7 38-821.01(Perm)(1E)(E)", "rp": "\u00a738-821.01(Perm)|(1E)|(E)", "x": "Animal welfare."}], "x": "\"Good Food Purchasing Program's core values\" means the following 5 core val"}, {"t": "(1F)", "p": "/us/dc/council/code/sections/38-821.01(Perm)#(1F)", "et": "para", "sc": "\u00a7 38-821.01(Perm)(1F)", "rp": "\u00a738-821.01(Perm)|(1F)", "x": "\"Health education\" means instruction of the District of Columbia Health Edu"}, {"t": "(1G)", "p": "/us/dc/council/code/sections/38-821.01(Perm)#(1G)", "et": "para", "sc": "\u00a7 38-821.01(Perm)(1G)", "rp": "\u00a738-821.01(Perm)|(1G)", "x": "Repealed."}, {"t": "(2)", "p": "/us/dc/council/code/sections/38-821.01(Perm)#(2)", "et": "para", "sc": "\u00a7 38-821.01(Perm)(2)", "rp": "\u00a738-821.01(Perm)|(2)", "x": "\"Healthy Youth and Schools Commission\" or \"Commission\" means the body estab"}, {"t": "(3)", "p": "/us/dc/council/code/sections/38-821.01(Perm)#(3)", "et": "para", "sc": "\u00a7 38-821.01(Perm)(3)", "rp": "\u00a738-821.01(Perm)|(3)", "x": "\"Locally grown\" means grown in Delaware, the District of Columbia, Maryland"}, {"t": "(4)", "p": "/us/dc/council/code/sections/38-821.01(Perm)#(4)", "et": "para", "sc": "\u00a7 38-821.01(Perm)(4)", "rp": "\u00a738-821.01(Perm)|(4)", "x": "\"Locally processed\" means processed at a facility in Delaware, the District"}, {"t": "(5)", "p": "/us/dc/council/code/sections/38-821.01(Perm)#(5)", "et": "para", "sc": "\u00a7 38-821.01(Perm)(5)", "rp": "\u00a738-821.01(Perm)|(5)", "x": "\"Meals\" means breakfast, lunch, or after-school snacks served as a part of "}, {"t": "(6)", "p": "/us/dc/council/code/sections/38-821.01(Perm)#(6)", "et": "para", "sc": "\u00a7 38-821.01(Perm)(6)", "rp": "\u00a738-821.01(Perm)|(6)", "x": "\"Moderate-to-vigorous physical activity\" means movement resulting in a subs"}, {"t": "(6A)", "p": "/us/dc/council/code/sections/38-821.01(Perm)#(6A)", "et": "para", "sc": "\u00a7 38-821.01(Perm)(6A)", "rp": "\u00a738-821.01(Perm)|(6A)", "x": "\"Participating private school\" means a private school that participates in "}, {"t": "(6B)", "p": "/us/dc/council/code/sections/38-821.01(Perm)#(6B)", "et": "para", "sc": "\u00a7 38-821.01(Perm)(6B)", "rp": "\u00a738-821.01(Perm)|(6B)", "x": "\"Physical activity\" means bodily movement, including walking, dancing, or g"}, {"t": "(6C)", "p": "/us/dc/council/code/sections/38-821.01(Perm)#(6C)", "et": "para", "sc": "\u00a7 38-821.01(Perm)(6C)", "rp": "\u00a738-821.01(Perm)|(6C)", "x": "\"Physical education\" means instruction based on the District of Columbia Ph"}, {"t": "(6D)", "p": "/us/dc/council/code/sections/38-821.01(Perm)#(6D)", "et": "para", "sc": "\u00a7 38-821.01(Perm)(6D)", "rp": "\u00a738-821.01(Perm)|(6D)", "c": [{"t": "(A)", "p": "/us/dc/council/code/sections/38-821.01(Perm)#(6D)(A)", "et": "para", "sc": "\u00a7 38-821.01(Perm)(6D)(A)", "rp": "\u00a738-821.01(Perm)|(6D)|(A)", "x": "Are free of animal products; and"}, {"t": "(B)", "p": "/us/dc/council/code/sections/38-821.01(Perm)#(6D)(B)", "et": "para", "sc": "\u00a7 38-821.01(Perm)(6D)(B)", "rp": "\u00a738-821.01(Perm)|(6D)|(B)", "x": "With respect to the meat or meat alternate component of a meal, provide a s"}], "x": "\"Plant-based food option\" means food or beverages that:"}, {"t": "(7)", "p": "/us/dc/council/code/sections/38-821.01(Perm)#(7)", "et": "para", "sc": "\u00a7 38-821.01(Perm)(7)", "rp": "\u00a738-821.01(Perm)|(7)", "x": "\"Public charter school\" means a school chartered under Chapter 18 of this t"}, {"t": "(8)", "p": "/us/dc/council/code/sections/38-821.01(Perm)#(8)", "et": "para", "sc": "\u00a7 38-821.01(Perm)(8)", "rp": "\u00a738-821.01(Perm)|(8)", "x": "\"Public school\" means a school operated by the District of Columbia Public "}, {"t": "(8A)", "p": "/us/dc/council/code/sections/38-821.01(Perm)#(8A)", "et": "para", "sc": "\u00a7 38-821.01(Perm)(8A)", "rp": "\u00a738-821.01(Perm)|(8A)", "c": [{"t": "(A)", "p": "/us/dc/council/code/sections/38-821.01(Perm)#(8A)(A)", "et": "para", "sc": "\u00a7 38-821.01(Perm)(8A)(A)", "rp": "\u00a738-821.01(Perm)|(8A)|(A)", "x": "Decrease the elevated lead concentration in a drinking water source to 5 pa"}, {"t": "(B)", "p": "/us/dc/council/code/sections/38-821.01(Perm)#(8A)(B)", "et": "para", "sc": "\u00a7 38-821.01(Perm)(8A)(B)", "rp": "\u00a738-821.01(Perm)|(8A)|(B)", "x": "Preclude people from consuming or cooking with water from a drinking water "}], "x": "\"Remediation steps\" means, at a minimum, actions to:"}, {"t": "(8B)", "p": "/us/dc/council/code/sections/38-821.01(Perm)#(8B)", "et": "para", "sc": "\u00a7 38-821.01(Perm)(8B)", "rp": "\u00a738-821.01(Perm)|(8B)", "x": "\"Self-operated school food service\" means a District-run program of plannin"}, {"t": "(8C)", "p": "/us/dc/council/code/sections/38-821.01(Perm)#(8C)", "et": "para", "sc": "\u00a7 38-821.01(Perm)(8C)", "rp": "\u00a738-821.01(Perm)|(8C)", "x": "\"Share table\" is a location where school community members can place unopen"}, {"t": "(9)", "p": "/us/dc/council/code/sections/38-821.01(Perm)#(9)", "et": "para", "sc": "\u00a7 38-821.01(Perm)(9)", "rp": "\u00a738-821.01(Perm)|(9)", "c": [{"t": "(A)", "p": "/us/dc/council/code/sections/38-821.01(Perm)#(9)(A)", "et": "para", "sc": "\u00a7 38-821.01(Perm)(9)(A)", "rp": "\u00a738-821.01(Perm)|(9)|(A)", "x": "Satisfy human food and fiber needs;"}, {"t": "(B)", "p": "/us/dc/council/code/sections/38-821.01(Perm)#(9)(B)", "et": "para", "sc": "\u00a7 38-821.01(Perm)(9)(B)", "rp": "\u00a738-821.01(Perm)|(9)|(B)", "x": "Enhance environmental quality and the natural resource base upon which the "}, {"t": "(C)", "p": "/us/dc/council/code/sections/38-821.01(Perm)#(9)(C)", "et": "para", "sc": "\u00a7 38-821.01(Perm)(9)(C)", "rp": "\u00a738-821.01(Perm)|(9)|(C)", "x": "Make the most efficient use of nonrenewable resources and on-farm resources"}, {"t": "(D)", "p": "/us/dc/council/code/sections/38-821.01(Perm)#(9)(D)", "et": "para", "sc": "\u00a7 38-821.01(Perm)(9)(D)", "rp": "\u00a738-821.01(Perm)|(9)|(D)", "x": "Sustain the economic viability of farm operations; and"}, {"t": "(E)", "p": "/us/dc/council/code/sections/38-821.01(Perm)#(9)(E)", "et": "para", "sc": "\u00a7 38-821.01(Perm)(9)(E)", "rp": "\u00a738-821.01(Perm)|(9)|(E)", "x": "Enhance the quality of life for farmers and society as a whole."}], "x": "\"Sustainable agriculture\" means an integrated system of plant and animal pr"}, {"t": "(10)", "p": "/us/dc/council/code/sections/38-821.01(Perm)#(10)", "et": "para", "sc": "\u00a7 38-821.01(Perm)(10)", "rp": "\u00a738-821.01(Perm)|(10)", "c": [{"t": "(A)", "p": "/us/dc/council/code/sections/38-821.01(Perm)#(10)(A)", "et": "para", "sc": "\u00a7 38-821.01(Perm)(10)(A)", "rp": "\u00a738-821.01(Perm)|(10)|(A)", "x": "\"Unprocessed\" means foods that are nearest their whole, raw, and natural st"}, {"t": "(B)", "p": "/us/dc/council/code/sections/38-821.01(Perm)#(10)(B)", "et": "para", "sc": "\u00a7 38-821.01(Perm)(10)(B)", "rp": "\u00a738-821.01(Perm)|(10)|(B)", "c": [{"t": "(i)", "p": "/us/dc/council/code/sections/38-821.01(Perm)#(10)(B)(i)", "et": "para", "sc": "\u00a7 38-821.01(Perm)(10)(B)(i)", "rp": "\u00a738-821.01(Perm)|(10)|(B)|(i)", "x": "Cooling, refrigerating, or freezing;"}, {"t": "(ii)", "p": "/us/dc/council/code/sections/38-821.01(Perm)#(10)(B)(ii)", "et": "para", "sc": "\u00a7 38-821.01(Perm)(10)(B)(ii)", "rp": "\u00a738-821.01(Perm)|(10)|(B)|(ii)", "x": "Size adjustment through size reduction made by peeling, slicing, dicing, cu"}, {"t": "(iii)", "p": "/us/dc/council/code/sections/38-821.01(Perm)#(10)(B)(iii)", "et": "para", "sc": "\u00a7 38-821.01(Perm)(10)(B)(iii)", "rp": "\u00a738-821.01(Perm)|(10)|(B)|(iii)", "x": "Drying or dehydration;"}, {"t": "(iv)", "p": "/us/dc/council/code/sections/38-821.01(Perm)#(10)(B)(iv)", "et": "para", "sc": "\u00a7 38-821.01(Perm)(10)(B)(iv)", "rp": "\u00a738-821.01(Perm)|(10)|(B)|(iv)", "x": "Washing;"}, {"t": "(v)", "p": "/us/dc/council/code/sections/38-821.01(Perm)#(10)(B)(v)", "et": "para", "sc": "\u00a7 38-821.01(Perm)(10)(B)(v)", "rp": "\u00a738-821.01(Perm)|(10)|(B)|(v)", "x": "The application of high water pressure or \"cold pasteurization\";"}, {"t": "(vi)", "p": "/us/dc/council/code/sections/38-821.01(Perm)#(10)(B)(vi)", "et": "para", "sc": "\u00a7 38-821.01(Perm)(10)(B)(vi)", "rp": "\u00a738-821.01(Perm)|(10)|(B)|(vi)", "x": "Packaging, such as placing eggs in cartons, and vacuum packing and bagging,"}, {"t": "(vii)", "p": "/us/dc/council/code/sections/38-821.01(Perm)#(10)(B)(vii)", "et": "para", "sc": "\u00a7 38-821.01(Perm)(10)(B)(vii)", "rp": "\u00a738-821.01(Perm)|(10)|(B)|(vii)", "x": "Butchering livestock, fish, or poultry; and"}, {"t": "(viii)", "p": "/us/dc/council/code/sections/38-821.01(Perm)#(10)(B)(viii)", "et": "para", "sc": "\u00a7 38-821.01(Perm)(10)(B)(viii)", "rp": "\u00a738-821.01(Perm)|(10)|(B)|(viii)", "x": "The pasteurization of milk."}], "x": "For the purposes of this paragraph, food which undergoes the following proc"}]}, {"t": "(11)", "p": "/us/dc/council/code/sections/38-821.01(Perm)#(11)", "et": "para", "sc": "\u00a7 38-821.01(Perm)(11)", "rp": "\u00a738-821.01(Perm)|(11)", "c": [{"t": "(A)", "p": "/us/dc/council/code/sections/38-821.01(Perm)#(11)(A)", "et": "para", "sc": "\u00a7 38-821.01(Perm)(11)(A)", "rp": "\u00a738-821.01(Perm)|(11)|(A)", "x": "Are free of meat, poultry, and seafood; and"}, {"t": "(B)", "p": "/us/dc/council/code/sections/38-821.01(Perm)#(11)(B)", "et": "para", "sc": "\u00a7 38-821.01(Perm)(11)(B)", "rp": "\u00a738-821.01(Perm)|(11)|(B)", "x": "With respect to the meat or meat alternate component of a meal, provide a s"}], "x": "\"Vegetarian food option\" means food or beverages that:"}], "u": true, "x": "For the purposes of this chapter, the term:"}]}