{
  "meta": {
    "build": {
      "build-date": "2025-06-24",
      "ci-build-number": "1.0.751",
      "ci-project": "DCCouncil/law-xml",
      "codified-date": "2025-06-17",
      "platform": {
        "reproducible": "false",
        "version": "2.12.10"
      },
      "repositories": [
        {
          "commit": "5ec078932655ef523ee34087f7a7ff6b4490b6fd",
          "name": "DCCouncil/law-xml"
        },
        {
          "commit": "65e1e5fd7fa319237e2b47453529ee832e980d74",
          "name": "DCCouncil/law-xml-codified-preview"
        }
      ]
    },
    "canonical-urls": {
      "html": "https://code.dccouncil.us",
      "html-bulk": "https://github.com/dccouncil/law-html",
      "law-git": "https://github.com/dccouncil/law.git",
      "static-assets": "https://github.com/dccouncil/law-static-assets",
      "xml-bulk": "https://github.com/dccouncil/law-xml"
    },
    "contact": {
      "email": "code@dccouncil.us"
    },
    "description": "Browse the laws and code of the District of Columbia",
    "redirects": [
      {
        "in": "/dc/council",
        "out": "/us/dc/council"
      }
    ]
  }
}