{
  "meta": {
    "build": {
      "build-date": "2026-05-08",
      "ci-build-number": "1.0.954",
      "ci-project": "DCCouncil/law-xml",
      "codified-date": "2026-04-29",
      "platform": {
        "reproducible": "false",
        "version": "2.12.10"
      },
      "repositories": [
        {
          "commit": "167f4a20b7e88dd456b0524174492ffc3d9eb70b",
          "name": "DCCouncil/law-xml"
        },
        {
          "commit": "6ff507c0a339d0fae6efc16e7e7f81d077f2ec72",
          "name": "DCCouncil/law-xml-codified-preview"
        }
      ]
    },
    "canonical-urls": {
      "html": "https://code.dccouncil.us",
      "html-bulk": "https://github.com/dccouncil/law-html",
      "law-git": "https://github.com/dccouncil/law.git",
      "static-assets": "https://github.com/dccouncil/law-static-assets",
      "xml-bulk": "https://github.com/dccouncil/law-xml"
    },
    "contact": {
      "email": "code@dccouncil.us"
    },
    "description": "Browse the laws and code of the District of Columbia",
    "redirects": [
      {
        "in": "/dc/council",
        "out": "/us/dc/council"
      }
    ]
  }
}