{
  "meta": {
    "build": {
      "build-date": "2025-02-11",
      "ci-build-number": "1.0.662",
      "ci-project": "DCCouncil/law-xml",
      "codified-date": "2025-02-03",
      "platform": {
        "reproducible": "false",
        "version": "2.12.7"
      },
      "repositories": [
        {
          "commit": "4d160682116224f2a717f1b5e5b6329564dd9bc8",
          "name": "DCCouncil/law-xml"
        },
        {
          "commit": "13608e1cd639c706fc0dbfc458a59f0b52f422a1",
          "name": "DCCouncil/law-xml-codified-preview"
        }
      ]
    },
    "canonical-urls": {
      "html": "https://code.dccouncil.us",
      "html-bulk": "https://github.com/dccouncil/law-html",
      "law-git": "https://github.com/dccouncil/law.git",
      "static-assets": "https://github.com/dccouncil/law-static-assets",
      "xml-bulk": "https://github.com/dccouncil/law-xml"
    },
    "contact": {
      "email": "code@dccouncil.us"
    },
    "description": "Browse the laws and code of the District of Columbia",
    "redirects": [
      {
        "in": "/dc/council",
        "out": "/us/dc/council"
      }
    ]
  }
}