{"t": "\u00a7 1\u2013350.01(Perm). Definitions.", "p": "/us/dc/council/code/sections/1-350.01(Perm)", "et": "section", "dj": "/us/dc/council/code/index.json", "fh": "/us/dc/council/code/sections/1-350.01(Perm)/index.html", "sc": "\u00a7 1-350.01(Perm)", "rp": "\u00a71-350.01(Perm)", "sp": "library|D.C. Code|99|1-350.01(Perm)", "c": [{"t": "(1)", "p": "/us/dc/council/code/sections/1-350.01(Perm)#(1)", "et": "para", "sc": "\u00a7 1-350.01(Perm)(1)", "rp": "\u00a71-350.01(Perm)|(1)", "x": "\u201cCentral Collection Unit\u201d means the Central Collection Unit established wit"}, {"t": "(2)", "p": "/us/dc/council/code/sections/1-350.01(Perm)#(2)", "et": "para", "sc": "\u00a7 1-350.01(Perm)(2)", "rp": "\u00a71-350.01(Perm)|(2)", "c": [{"t": "(A)", "p": "/us/dc/council/code/sections/1-350.01(Perm)#(2)(A)", "et": "para", "sc": "\u00a7 1-350.01(Perm)(2)(A)", "rp": "\u00a71-350.01(Perm)|(2)|(A)", "x": "Any financial obligation owed by a person to a District agency that remains"}, {"t": "(B)", "p": "/us/dc/council/code/sections/1-350.01(Perm)#(2)(B)", "et": "para", "sc": "\u00a7 1-350.01(Perm)(2)(B)", "rp": "\u00a71-350.01(Perm)|(2)|(B)", "x": "A fine issued by the Alcoholic Beverage and Cannabis Administration pursuan"}], "x": "\"Delinquent debt\" means:"}, {"t": "(3)", "p": "/us/dc/council/code/sections/1-350.01(Perm)#(3)", "et": "para", "sc": "\u00a7 1-350.01(Perm)(3)", "rp": "\u00a71-350.01(Perm)|(3)", "x": "\u201cDelinquent Debt Fund\u201d or \u201cFund\u201d means the Delinquent Debt Fund established"}, {"t": "(4)", "p": "/us/dc/council/code/sections/1-350.01(Perm)#(4)", "et": "para", "sc": "\u00a7 1-350.01(Perm)(4)", "rp": "\u00a71-350.01(Perm)|(4)", "x": "\u201cDistrict agency\u201d means any District office, department, or agency, includi"}, {"t": "(5)", "p": "/us/dc/council/code/sections/1-350.01(Perm)#(5)", "et": "para", "sc": "\u00a7 1-350.01(Perm)(5)", "rp": "\u00a71-350.01(Perm)|(5)", "x": "\u201cPerson\u201d means any natural person, trust, corporation, limited liability co"}]}