{"t": "\u00a7 50\u20131501.02g(Perm). Issuance of parks and recreation motor vehicle identification tags.", "p": "/us/dc/council/code/sections/50-1501.02g(Perm)", "et": "section", "dj": "/us/dc/council/code/index.json", "fh": "/us/dc/council/code/sections/50-1501.02g(Perm)/index.html", "sc": "\u00a7 50-1501.02g(Perm)", "rp": "\u00a750-1501.02g(Perm)", "sp": "library|D.C. Code|99|50-1501.02g(Perm)", "c": [{"t": "(a)", "p": "/us/dc/council/code/sections/50-1501.02g(Perm)#(a)", "et": "para", "sc": "\u00a7 50-1501.02g(Perm)(a)", "rp": "\u00a750-1501.02g(Perm)|(a)", "x": "The Mayor shall design and make available for issue one or more parks and r"}, {"t": "(b)", "p": "/us/dc/council/code/sections/50-1501.02g(Perm)#(b)", "et": "para", "sc": "\u00a7 50-1501.02g(Perm)(b)", "rp": "\u00a750-1501.02g(Perm)|(b)", "c": [{"t": "(1)", "p": "/us/dc/council/code/sections/50-1501.02g(Perm)#(b)(1)", "et": "para", "sc": "\u00a7 50-1501.02g(Perm)(b)(1)", "rp": "\u00a750-1501.02g(Perm)|(b)|(1)", "x": "A resident ordering a parks and recreation motor vehicle identification tag"}, {"t": "(2)", "p": "/us/dc/council/code/sections/50-1501.02g(Perm)#(b)(2)", "et": "para", "sc": "\u00a7 50-1501.02g(Perm)(b)(2)", "rp": "\u00a750-1501.02g(Perm)|(b)|(2)", "x": "The application fee and annual display fee shall be deposited in the Recrea"}]}]}